ShelfSimplify/ShelfSimplify.py
ShelfSimplify/__init__.py
ShelfSimplify/main.py
ShelfSimplify-0.8.0.dist-info/LICENSE
ShelfSimplify-0.8.0.dist-info/METADATA
ShelfSimplify-0.8.0.dist-info/WHEEL
ShelfSimplify-0.8.0.dist-info/top_level.txt
ShelfSimplify-0.8.0.dist-info/RECORD
