Metadata-Version: 2.1
Name: ShelfSimplify
Version: 0.8.0
License-File: LICENSE
